Workbook

Sheet Today
B2: Today's Practice | E2: =Settings!$B$8-TODAY()
B3: =TEXT(TODAY(),"dddd, d mmmm yyyy") | E3: days to placements
B5: Progress | D5: Done | E5: Total
B6: LeetCode | C6: =SPARKLINE(D6/E6,{"charttype","bar";"max",1;"color1","#1D4ED8";"empty","zero"}) | D6: =COUNTIFS(Plan!$C$2:$C$625,"LeetCode",Plan!$G$2:$G$625,TRUE) | E6: =COUNTIF(Plan!$C$2:$C$625,"LeetCode")
B7: SQL | C7: =SPARKLINE(D7/E7,{"charttype","bar";"max",1;"color1","#1D4ED8";"empty","zero"}) | D7: =COUNTIFS(Plan!$C$2:$C$625,"SQL",Plan!$G$2:$G$625,TRUE) | E7: =COUNTIF(Plan!$C$2:$C$625,"SQL")
B8: Codeforces | C8: =SPARKLINE(D8/E8,{"charttype","bar";"max",1;"color1","#1D4ED8";"empty","zero"}) | D8: =COUNTIFS(Plan!$C$2:$C$625,"Codeforces",Plan!$G$2:$G$625,TRUE) | E8: =COUNTIF(Plan!$C$2:$C$625,"Codeforces")
B9: Solved today | D9: =COUNTIF(Plan!$H$2:$H$625,TODAY())
B11: ▶ Do these today | C11: Tick them in the Plan tab. Finish early? Keep going in Plan: tomorrow's problems slide up.
B12: Track | C12: Problem (click to open) | D12: Level | E12: Phase
B13: =ARRAYFORMULA(IF(H13:H24="","",H13:H24)) | C13: =ARRAYFORMULA(IF(K13:K24="","",HYPERLINK(IF(LEFT(K13:K24,4)="http",K13:K24,"https://leetcode.com/problems/"&K13:K24&"/"),I13:I24))) | D13: =ARRAYFORMULA(IF(J13:J24="","",J13:J24)) | E13: =IFERROR(INDEX(Plan!F2:F625,MATCH("▶ Today",Plan!B2:B625,0)),"") | H13: =IFERROR(ARRAY_CONSTRAIN(FILTER({Plan!C2:C625,Plan!D2:D625,Plan!E2:E625,Plan!L2:L625},Plan!B2:B625="▶ Today"),12,4),"🎉 All done for today. Do extra in Plan if you have time.")
B26: ↻ Revisit today (redo from memory) | C26: Problems you needed help on, coming back 3, 7 and 21 days after you solved them.
B27: Track | C27: Problem (click to open) | D27: Help used | E27: Solved on
B28: =ARRAYFORMULA(IF(H28:H40="","",H28:H40)) | C28: =ARRAYFORMULA(IF(K28:K40="","",HYPERLINK(IF(LEFT(K28:K40,4)="http",K28:K40,"https://leetcode.com/problems/"&K28:K40&"/"),I28:I40))) | D28: =ARRAYFORMULA(IF(J28:J40="","",J28:J40)) | H28: =IFERROR(ARRAY_CONSTRAIN(FILTER({Plan!C2:C625,Plan!D2:D625,Plan!I2:I625,Plan!L2:L625},((Plan!I2:I625="Hint")+(Plan!I2:I625="Editorial"))*((IFERROR(TODAY()-Plan!H2:H625,0)=3)+(IFERROR(TODAY()-Plan!H2:H625,0)=7)+(IFERROR(TODAY()-Plan!H2:H625,0)=21))),13,4),"Nothing to revisit today.")

Sheet Plan
A1: Due | B1: Status | C1: Track | D1: Problem (click to open) | E1: Level | F1: Phase | G1: Done | H1: Done on | I1: Needed help? | J1: Key insight (1 line) | K1: Topic (spoiler) | L1: url | M1: title | N1: slot | O1: quota
A2: =ARRAYFORMULA(IF(C2:C625="","",IF(G2:G625=TRUE,H2:H625,IF(C2:C625="Codeforces",IF(((TODAY()-WEEKDAY(TODAY(),2)+1)+5+7*INT(N2:N625/O2:O625))<TODAY(),TODAY(),((TODAY()-WEEKDAY(TODAY(),2)+1)+5+7*INT(N2:N625/O2:O625))),TODAY()+INT(N2:N625/O2:O625))))) | B2: =ARRAYFORMULA(IF(C2:C625="","",IF(G2:G625=TRUE,"✓ Done",IF(A2:A625=TODAY(),"▶ Today",IF(A2:A625=TODAY()+1,"Tomorrow",TEXT(A2:A625,"ddd, dd mmm")))))) | C2: LeetCode | D2: =ARRAYFORMULA(IF(L2:L625="","",HYPERLINK(IF(LEFT(L2:L625,4)="http",L2:L625,"https://leetcode.com/problems/"&L2:L625&"/"),IF(M2:M625="",PROPER(SUBSTITUTE(L2:L625,"-"," ")),M2:M625)))) | E2: Medium | F2: =ARRAYFORMULA(IF(C2:C625="","",IF(ROW(C2:C625)<220,"1 · Unseen Mediums",IF(ROW(C2:C625)<427,"2 · Medium-Hard",IF(ROW(C2:C625)<577,"3 · OA Simulation","4 · Revision"))))) | H2: =IF(G2=TRUE,IF(H2="",TODAY(),H2),"") | K2: Backtracking, Tree | L2: path-sum-ii | M2: Path Sum II | N2: =ARRAYFORMULA(IF(G2:G625=TRUE,"",MMULT((C2:C625=TRANSPOSE(C2:C625))*(ROW(C2:C625)>=TRANSPOSE(ROW(C2:C625)))*(TRANSPOSE(G2:G625)<>TRUE),SIGN(ROW(C2:C625)))-1+IF(C2:C625="Codeforces",COUNTIFS(C2:C625,"Codeforces",H2:H625,">="&(TODAY()-WEEKDAY(TODAY(),2)+1)),MMULT((C2:C625=TRANSPOSE(C2:C625))*IFERROR(TRANSPOSE(H2:H625)=TODAY(),FALSE),SIGN(ROW(C2:C625)))))) | O2: =ARRAYFORMULA(IF(C2:C625="LeetCode",Settings!$B$4,IF(C2:C625="SQL",Settings!$B$5,Settings!$B$6)))
C3: LeetCode | E3: Medium | H3: =IF(G3=TRUE,IF(H3="",TODAY(),H3),"") | K3: Array, Hash Table | L3: count-triplets-that-can-form-two-arrays-of-equal-xor
C4: SQL | E4: Easy | H4: =IF(G4=TRUE,IF(H4="",TODAY(),H4),"") | K4: SQL | L4: combine-two-tables
C5: LeetCode | E5: Medium | H5: =IF(G5=TRUE,IF(H5="",TODAY(),H5),"") | K5: Array, Hash Table | L5: longest-well-performing-interval
C6: LeetCode | E6: Medium | H6: =IF(G6=TRUE,IF(H6="",TODAY(),H6),"") | K6: Array, Stack | L6: construct-binary-search-tree-from-preorder-traversal
C7: SQL | E7: Easy | H7: =IF(G7=TRUE,IF(H7="",TODAY(),H7),"") | K7: SQL | L7: rising-temperature
C8: Codeforces | E8: CF 1200 | H8: =IF(G8=TRUE,IF(H8="",TODAY(),H8),"") | K8: greedy | L8: https://codeforces.com/problemset?order=BY_SOLVED_DESC&tags=greedy,1200-1200 | M8: Most-solved unsolved: greedy · 1200
C9: Codeforces | E9: CF 1300 | H9: =IF(G9=TRUE,IF(H9="",TODAY(),H9),"") | K9: constructive algorithms | L9: https://codeforces.com/problemset?order=BY_SOLVED_DESC&tags=constructive%20algorithms,1300-1300 | M9: Most-solved unsolved: constructive algorithms · 1300
C10: LeetCode | E10: Medium | H10: =IF(G10=TRUE,IF(H10="",TODAY(),H10),"") | K10: Array, Hash Table | L10: construct-binary-tree-from-preorder-and-postorder-traversal
C11: LeetCode | E11: Medium | H11: =IF(G11=TRUE,IF(H11="",TODAY(),H11),"") | K11: Array, Sliding Window | L11: grumpy-bookstore-owner
C12: SQL | E12: Easy | H12: =IF(G12=TRUE,IF(H12="",TODAY(),H12),"") | K12: SQL | L12: customer-who-visited-but-did-not-make-any-transactions
C13: LeetCode | E13: Medium | H13: =IF(G13=TRUE,IF(H13="",TODAY(),H13),"") | K13: Linked List, Divide and Conquer | L13: convert-sorted-list-to-binary-search-tree
C14: LeetCode | E14: Medium | H14: =IF(G14=TRUE,IF(H14="",TODAY(),H14),"") | K14: Array, Two Pointers | L14: valid-triangle-number
C15: SQL | E15: Easy | H15: =IF(G15=TRUE,IF(H15="",TODAY(),H15),"") | K15: SQL | L15: recyclable-and-low-fat-products
C16: LeetCode | E16: Medium | H16: =IF(G16=TRUE,IF(H16="",TODAY(),H16),"") | K16: Hash Table, String | L16: minimum-number-of-steps-to-make-two-strings-anagram
C17: LeetCode | E17: Medium | H17: =IF(G17=TRUE,IF(H17="",TODAY(),H17),"") | K17: Hash Table, Tree | L17: all-nodes-distance-k-in-binary-tree
C18: SQL | E18: Easy | H18: =IF(G18=TRUE,IF(H18="",TODAY(),H18),"") | K18: SQL | L18: big-countries
C19: LeetCode | E19: Medium | H19: =IF(G19=TRUE,IF(H19="",TODAY(),H19),"") | K19: Hash Table, Tree | L19: most-frequent-subtree-sum
C20: LeetCode | E20: Medium | H20: =IF(G20=TRUE,IF(H20="",TODAY(),H20),"") | K20: Math, Bit Manipulation | L20: k-th-symbol-in-grammar
C21: SQL | E21: Easy | H21: =IF(G21=TRUE,IF(H21="",TODAY(),H21),"") | K21: SQL | L21: employees-earning-more-than-their-managers
... C30: SQL | E30: Easy | H30: =IF(G30=TRUE,IF(H30="",TODAY(),H30),"") | K30: SQL | L30: find-customer-referee
C31: Codeforces | E31: CF 1200 | H31: =IF(G31=TRUE,IF(H31="",TODAY(),H31),"") | K31: math | L31: https://codeforces.com/problemset?order=BY_SOLVED_DESC&tags=math,1200-1200 | M31: Most-solved unsolved: math · 1200
C32: Codeforces | E32: CF 1300 | H32: =IF(G32=TRUE,IF(H32="",TODAY(),H32),"") | K32: implementation | L32: https://codeforces.com/problemset?order=BY_SOLVED_DESC&tags=implementation,1300-1300 | M32: Most-solved unsolved: implementation · 1300
C33: LeetCode | E33: Medium | H33: =IF(G33=TRUE,IF(H33="",TODAY(),H33),"") | K33: Math, Binary Search | L33: maximum-value-at-a-given-index-in-a-bounded-array
C34: LeetCode | E34: Medium | H34: =IF(G34=TRUE,IF(H34="",TODAY(),H34),"") | K34: Math, String | L34: number-of-substrings-with-only-1s
C35: SQL | E35: Easy | H35: =IF(G35=TRUE,IF(H35="",TODAY(),H35),"") | K35: SQL | L35: average-time-of-process-per-machine
C36: LeetCode | E36: Medium | H36: =IF(G36=TRUE,IF(H36="",TODAY(),H36),"") | K36: Array, Stack | L36: minimum-deletions-to-make-array-beautiful
C37: LeetCode | E37: Medium | H37: =IF(G37=TRUE,IF(H37="",TODAY(),H37),"") | K37: Math | L37: angle-between-hands-of-a-clock
C38: SQL | E38: Easy | H38: =IF(G38=TRUE,IF(H38="",TODAY(),H38),"") | K38: SQL | L38: duplicate-emails
C39: LeetCode | E39: Medium | H39: =IF(G39=TRUE,IF(H39="",TODAY(),H39),"") | K39: String, Stack | L39: score-of-parentheses
C40: LeetCode | E40: Medium | H40: =IF(G40=TRUE,IF(H40="",TODAY(),H40),"") | K40: Divide and Conquer, Greedy | L40: balance-a-binary-search-tree
C41: SQL | E41: Easy | H41: =IF(G41=TRUE,IF(H41="",TODAY(),H41),"") | K41: SQL | L41: article-views-i | M41: Article Views I
C42: LeetCode | E42: Medium | H42: =IF(G42=TRUE,IF(H42="",TODAY(),H42),"") | K42: Tree, Depth-First Search | L42: longest-univalue-path
C43: LeetCode | E43: Medium | H43: =IF(G43=TRUE,IF(H43="",TODAY(),H43),"") | K43: Array, Two Pointers | L43: rearrange-array-elements-by-sign
C44: SQL | E44: Easy | H44: =IF(G44=TRUE,IF(H44="",TODAY(),H44),"") | K44: SQL | L44: delete-duplicate-emails
C45: LeetCode | E45: Medium | H45: =IF(G45=TRUE,IF(H45="",TODAY(),H45),"") | K45: Array, Math | L45: minimum-time-difference
C46: LeetCode | E46: Medium | H46: =IF(G46=TRUE,IF(H46="",TODAY(),H46),"") | K46: Tree, Depth-First Search | L46: maximum-difference-between-node-and-ancestor
C47: SQL | E47: Easy | H47: =IF(G47=TRUE,IF(H47="",TODAY(),H47),"") | K47: SQL | L47: replace-employee-id-with-the-unique-identifier
C48: LeetCode | E48: Medium | H48: =IF(G48=TRUE,IF(H48="",TODAY(),H48),"") | K48: Array, Greedy | L48: increasing-triplet-subsequence
C49: LeetCode | E49: Medium | H49: =IF(G49=TRUE,IF(H49="",TODAY(),H49),"") | K49: Tree, Depth-First Search | L49: maximum-product-of-splitted-binary-tree
C50: SQL | E50: Easy | H50: =IF(G50=TRUE,IF(H50="",TODAY(),H50),"") | K50: SQL | L50: average-selling-price
C51: LeetCode | E51: Medium | H51: =IF(G51=TRUE,IF(H51="",TODAY(),H51),"") | K51: Array, Prefix Sum | L51: number-of-ways-to-split-array
C52: LeetCode | E52: Medium | H52: =IF(G52=TRUE,IF(H52="",TODAY(),H52),"") | K52: Array, String | L52: maximum-product-of-word-lengths
C53: SQL | E53: Easy | H53: =IF(G53=TRUE,IF(H53="",TODAY(),H53),"") | K53: SQL | L53: swap-sex-of-employees
C54: Codeforces | E54: CF 1200 | H54: =IF(G54=TRUE,IF(H54="",TODAY(),H54),"") | K54: binary search | L54: https://codeforces.com/problemset?order=BY_SOLVED_DESC&tags=binary%20search,1200-1200 | M54: Most-solved unsolved: binary search · 1200
C55: Codeforces | E55: CF 1300 | H55: =IF(G55=TRUE,IF(H55="",TODAY(),H55),"") | K55: two pointers | L55: https://codeforces.com/problemset?order=BY_SOLVED_DESC&tags=two%20pointers,1300-1300 | M55: Most-solved unsolved: two pointers · 1300
C56: LeetCode | E56: Medium | H56: =IF(G56=TRUE,IF(H56="",TODAY(),H56),"") | K56: Array, Queue | L56: continuous-subarrays
C57: LeetCode | E57: Medium | H57: =IF(G57=TRUE,IF(H57="",TODAY(),H57),"") | K57: Binary Search, Bit Manipulation | L57: count-complete-tree-nodes
C58: SQL | E58: Easy | H58: =IF(G58=TRUE,IF(H58="",TODAY(),H58),"") | K58: SQL | L58: group-sold-products-by-the-date
C59: LeetCode | E59: Medium | H59: =IF(G59=TRUE,IF(H59="",TODAY(),H59),"") | K59: Array, Hash Table | L59: binary-subarrays-with-sum
C60: LeetCode | E60: Medium | H60: =IF(G60=TRUE,IF(H60="",TODAY(),H60),"") | K60: Array, Binary Search | L60: magnetic-force-between-two-balls
C61: SQL | E61: Easy | H61: =IF(G61=TRUE,IF(H61="",TODAY(),H61),"") | K61: SQL | L61: employee-bonus
C62: LeetCode | E62: Medium | H62: =IF(G62=TRUE,IF(H62="",TODAY(),H62),"") | K62: Array, Queue | L62: longest-continuous-subarray-with-absolute-diff-less-than-or-equal-to-limit
C63: LeetCode | E63: Medium | H63: =IF(G63=TRUE,IF(H63="",TODAY(),H63),"") | K63: Two Pointers, String | L63: make-string-a-subsequence-using-cyclic-increments
C64: SQL | E64: Easy | H64: =IF(G64=TRUE,IF(H64="",TODAY(),H64),"") | K64: SQL | L64: not-boring-movies
C65: LeetCode | E65: Medium | H65: =IF(G65=TRUE,IF(H65="",TODAY(),H65),"") | K65: Array, Hash Table | L65: word-subsets
C66: LeetCode | E66: Medium | H66: =IF(G66=TRUE,IF(H66="",TODAY(),H66),"") | K66: Array, Simulation | L66: average-waiting-time
C67: SQL | E67: Easy | H67: =IF(G67=TRUE,IF(H67="",TODAY(),H67),"") | K67: SQL | L67: product-sales-analysis-i | M67: Product Sales Analysis I
C68: LeetCode | E68: Medium | H68: =IF(G68=TRUE,IF(H68="",TODAY(),H68),"") | K68: Depth-First Search, Breadth-First Search | L68: number-of-operations-to-make-network-connected
C69: LeetCode | E69: Medium | H69: =IF(G69=TRUE,IF(H69="",TODAY(),H69),"") | K69: Hash Table, Linked List | L69: remove-zero-sum-consecutive-nodes-from-linked-list
C70: SQL | E70: Easy | H70: =IF(G70=TRUE,IF(H70="",TODAY(),H70),"") | K70: SQL | L70: reformat-department-table
C71: LeetCode | E71: Medium | H71: =IF(G71=TRUE,IF(H71="",TODAY(),H71),"") | K71: Array, Breadth-First Search | L71: nearest-exit-from-entrance-in-maze
C72: LeetCode | E72: Medium | H72: =IF(G72=TRUE,IF(H72="",TODAY(),H72),"") | K72: Array, Linked List | L72: next-greater-node-in-linked-list
C73: SQL | E73: Medium | H73: =IF(G73=TRUE,IF(H73="",TODAY(),H73),"") | K73: SQL | L73: seasonal-sales-analysis
C74: LeetCode | E74: Medium | H74: =IF(G74=TRUE,IF(H74="",TODAY(),H74),"") | K74: Array, Hash Table | L74: majority-element-ii | M74: Majority Element II
C75: LeetCode | E75: Medium | H75: =IF(G75=TRUE,IF(H75="",TODAY(),H75),"") | K75: Array, Hash Table | L75: find-all-duplicates-in-an-array
C76: SQL | E76: Easy | H76: =IF(G76=TRUE,IF(H76="",TODAY(),H76),"") | K76: SQL | L76: daily-leads-and-partners
C77: Codeforces | E77: CF 1200 | H77: =IF(G77=TRUE,IF(H77="",TODAY(),H77),"") | K77: sortings | L77: https://codeforces.com/problemset?order=BY_SOLVED_DESC&tags=sortings,1200-1200 | M77: Most-solved unsolved: sortings · 1200
C78: Codeforces | E78: CF 1300 | H78: =IF(G78=TRUE,IF(H78="",TODAY(),H78),"") | K78: strings | L78: https://codeforces.com/problemset?order=BY_SOLVED_DESC&tags=strings,1300-1300 | M78: Most-solved unsolved: strings · 1300
C79: LeetCode | E79: Medium | H79: =IF(G79=TRUE,IF(H79="",TODAY(),H79),"") | K79: Math, String | L79: remove-colored-pieces-if-both-neighbors-are-the-same-color
C80: LeetCode | E80: Medium | H80: =IF(G80=TRUE,IF(H80="",TODAY(),H80),"") | K80: String, Stack | L80: reverse-substrings-between-each-pair-of-parentheses
C81: SQL | E81: Easy | H81: =IF(G81=TRUE,IF(H81="",TODAY(),H81),"") | K81: SQL | L81: find-users-with-high-token-usage
C82: LeetCode | E82: Medium | H82: =IF(G82=TRUE,IF(H82="",TODAY(),H82),"") | K82: Array, Hash Table | L82: count-the-number-of-good-subarrays
C83: LeetCode | E83: Medium | H83: =IF(G83=TRUE,IF(H83="",TODAY(),H83),"") | K83: Array, Binary Search | L83: find-the-smallest-divisor-given-a-threshold
C84: SQL | E84: Easy | H84: =IF(G84=TRUE,IF(H84="",TODAY(),H84),"") | K84: SQL | L84: find-books-with-no-available-copies
C85: LeetCode | E85: Medium | H85: =IF(G85=TRUE,IF(H85="",TODAY(),H85),"") | K85: Array, Math | L85: number-of-laser-beams-in-a-bank
C86: LeetCode | E86: Medium | H86: =IF(G86=TRUE,IF(H86="",TODAY(),H86),"") | K86: Linked List, Depth-First Search | L86: flatten-a-multilevel-doubly-linked-list
C87: SQL | E87: Easy | H87: =IF(G87=TRUE,IF(H87="",TODAY(),H87),"") | K87: SQL | L87: invalid-tweets
C88: LeetCode | E88: Medium | H88: =IF(G88=TRUE,IF(H88="",TODAY(),H88),"") | K88: Array, Two Pointers | L88: shortest-subarray-to-be-removed-to-make-array-sorted
C89: LeetCode | E89: Medium | H89: =IF(G89=TRUE,IF(H89="",TODAY(),H89),"") | K89: Array, Hash Table | L89: restore-the-array-from-adjacent-pairs
C90: SQL | E90: Medium | H90: =IF(G90=TRUE,IF(H90="",TODAY(),H90),"") | K90: SQL | L90: analyze-subscription-conversion
C91: LeetCode | E91: Medium | H91: =IF(G91=TRUE,IF(H91="",TODAY(),H91),"") | K91: Array, Binary Search | L91: subarray-product-less-than-k
C92: LeetCode | E92: Medium | H92: =IF(G92=TRUE,IF(H92="",TODAY(),H92),"") | K92: Array, Backtracking | L92: combination-sum-iii | M92: Combination Sum III
C93: SQL | E93: Medium | H93: =IF(G93=TRUE,IF(H93="",TODAY(),H93),"") | K93: SQL | L93: find-golden-hour-customers
C94: LeetCode | E94: Medium | H94: =IF(G94=TRUE,IF(H94="",TODAY(),H94),"") | K94: Array, Hash Table | L94: reduce-array-size-to-the-half
C95: LeetCode | E95: Medium | H95: =IF(G95=TRUE,IF(H95="",TODAY(),H95),"") | K95: Tree, Depth-First Search | L95: recover-binary-search-tree
C96: SQL | E96: Medium | H96: =IF(G96=TRUE,IF(H96="",TODAY(),H96),"") | K96: SQL | L96: market-analysis-i | M96: Market Analysis I
C97: LeetCode | E97: Medium | H97: =IF(G97=TRUE,IF(H97="",TODAY(),H97),"") | K97: Array, Math | L97: find-the-winner-of-the-circular-game
C98: LeetCode | E98: Medium | H98: =IF(G98=TRUE,IF(H98="",TODAY(),H98),"") | K98: Array, Binary Search | L98: max-consecutive-ones-iii | M98: Max Consecutive Ones III
C99: SQL | E99: Medium | H99: =IF(G99=TRUE,IF(H99="",TODAY(),H99),"") | K99: SQL | L99: find-books-with-polarized-opinions
C100: Codeforces | E100: CF 1200 | H100: =IF(G100=TRUE,IF(H100="",TODAY(),H100),"") | K100: dp | L100: https://codeforces.com/problemset?order=BY_SOLVED_DESC&tags=dp,1200-1200 | M100: Most-solved unsolved: dp · 1200
C101: Codeforces | E101: CF 1300 | H101: =IF(G101=TRUE,IF(H101="",TODAY(),H101),"") | K101: graphs | L101: https://codeforces.com/problemset?order=BY_SOLVED_DESC&tags=graphs,1300-1300 | M101: Most-solved unsolved: graphs · 1300
C102: LeetCode | E102: Medium | H102: =IF(G102=TRUE,IF(H102="",TODAY(),H102),"") | K102: Array, Sorting | L102: maximum-gap
C103: LeetCode | E103: Medium | H103: =IF(G103=TRUE,IF(H103="",TODAY(),H103),"") | K103: Hash Table, Depth-First Search | L103: most-stones-removed-with-same-row-or-column
C104: SQL | E104: Medium | H104: =IF(G104=TRUE,IF(H104="",TODAY(),H104),"") | K104: SQL | L104: friend-requests-ii-who-has-the-most-friends
C105: LeetCode | E105: Medium | H105: =IF(G105=TRUE,IF(H105="",TODAY(),H105),"") | K105: Array, Stack | L105: design-a-stack-with-increment-operation
C106: LeetCode | E106: Medium | H106: =IF(G106=TRUE,IF(H106="",TODAY(),H106),"") | K106: Array, Two Pointers | L106: shortest-unsorted-continuous-subarray
C107: SQL | E107: Easy | H107: =IF(G107=TRUE,IF(H107="",TODAY(),H107),"") | K107: SQL | L107: list-the-products-ordered-in-a-period
C108: LeetCode | E108: Medium | H108: =IF(G108=TRUE,IF(H108="",TODAY(),H108),"") | K108: Array, Binary Search | L108: maximum-white-tiles-covered-by-a-carpet
...

Sheet How to Use
B2: How to use this tracker
B4: One-time setup (1 minute)
B5: 1 | C5: Go to the Plan tab, click the column letter G (Done), then Insert → Checkbox.
B6: 2 | C6: File → Settings → Calculation → Iterative calculation: ON. This lets 'Done on' remember the day you ticked a box.
B7: Every day
B8: 1 | C8: Open the Today tab. It lists today's minimum: 2 LeetCode + 1 SQL (+2 Codeforces on Saturdays).
B9: 2 | C9: Click a problem name to open it on LeetCode / Codeforces. Topic tags are hidden on purpose.
B10: 3 | C10: When solved, tick it in the Plan tab (green rows = today) and pick Solo / Hint / Editorial.
B11: 4 | C11: Got time? Keep ticking the next rows in Plan. Everything after slides one step earlier, so tomorrow still has a full minimum.
B12: 5 | C12: Missed a day? Nothing piles up. Unfinished problems simply roll to today.
B13: 6 | C13: Problems marked Hint or Editorial come back on the Today tab after 3, 7 and 21 days.
B14: Tips
B15: • | C15: Topic (spoiler) column: the text is hidden. Click the cell and read it in the formula bar after you solve.
B16: • | C16: Change daily counts in the Settings tab. Roadmap tab has the phase plan.
B17: • | C17: Already solved a problem? Tick it anyway and mark Solo, or replace the row with a new one.

Sheet Roadmap
B2: Roadmap · Oct 2026 → May 2027
B4: Phase | C4: Dates | D4: LeetCode | E4: Codeforces (Sat) | F4: SQL | G4: Goal
B5: 1 · Unseen Mediums | C5: Oct 23 – Dec 27 | D5: Random Mediums from the most-asked OA topics, tags hidden. No DP yet. | E5: 1200–1300 | F5: Easy → Medium | G5: Solve a random Medium solo in < 30 min
B6: 2 · Medium-Hard | C6: Dec 28 – Feb 28 | D6: 70% Medium / 30% Hard. Common DP patterns start (about 1 in 4). | E6: 1400–1500 | F6: Medium | G6: Hards feel approachable
B7: 3 · OA Simulation | C7: Mar 1 – Apr 15 | D7: 50% Medium / 50% Hard. Twice a week, do 3 in 90 min with no hints. | E7: 1500–1700 | F7: Medium/Hard, then round 2 | G7: Pass a 90-min OA mock
B8: 4 · Revision | C8: Apr 16 – May 1 | D8: Mediums plus the revisit queue. No new topics. | E8: 1600 | F8: Round 2 | G8: Calm and sharp
B10: Rules for every new problem
B11: 1. | C11: Read it and write down the constraints before thinking of an approach.
B12: 2. | C12: Think for 25 min before any hint: brute force → why it is slow → what to optimise.
B13: 3. | C13: Write a one-line key insight. That line is what you revise.
B14: 4. | C14: Sunday: LeetCode Weekly Contest (8:00 AM IST). Upsolve what you missed.

Sheet Settings
A1: Settings
A2: Change the blue numbers. The whole schedule re-flows instantly.
A4: LeetCode problems per day | B4: 2 | C4: Your daily minimum
A5: SQL problems per day | B5: 1
A6: Codeforces problems per week (Saturday) | B6: 2
A8: Placement date | B8: 46508
A10: Problem sources: LeetCode problems are free (non-premium), well-liked, and exclude the NeetCode 150/250 lists you have likely already done. SQL = every free LeetCode database problem, then a second round of re-solving. Codeforces links open the problemset filtered by topic and rating; solve the first one you haven't solved.
